{
  "verse_key": "16:65",
  "ayah_number": 1966,
  "text_uthmani": "وَٱللَّهُ أَنزَلَ مِنَ ٱلسَّمَآءِ مَآءًۭ فَأَحْيَا بِهِ ٱلْأَرْضَ بَعْدَ مَوْتِهَآ ۚ إِنَّ فِى ذَٰلِكَ لَءَايَةًۭ لِّقَوْمٍۢ يَسْمَعُونَ",
  "translation_en": "AND GOD sends down water from the skies, giving life thereby to the earth after it had been lifeless: in this, behold, there is a message indeed for people who [are willing to] listen.",
  "audio_url": "https://cdn.islamic.network/quran/audio/128/ar.alafasy/1966.mp3",
  "segments": [],
  "segment_present": false
}
