{
  "verse_key": "33:48",
  "ayah_number": 3581,
  "text_uthmani": "وَلَا تُطِعِ ٱلْكَٰفِرِينَ وَٱلْمُنَٰفِقِينَ وَدَعْ أَذَىٰهُمْ وَتَوَكَّلْ عَلَى ٱللَّهِ ۚ وَكَفَىٰ بِٱللَّهِ وَكِيلًۭا",
  "translation_en": "and defer not to [the likes and dislikes of] the deniers of the truth and the hypocrites, and disregard their hurtful talk, and place thy trust in God: for none is as worthy of trust as God.",
  "audio_url": "https://cdn.islamic.network/quran/audio/128/ar.alafasy/3581.mp3",
  "segments": [],
  "segment_present": false
}
