{
  "verse_key": "14:13",
  "ayah_number": 1763,
  "text_uthmani": "وَقَالَ ٱلَّذِينَ كَفَرُوا۟ لِرُسُلِهِمْ لَنُخْرِجَنَّكُم مِّنْ أَرْضِنَآ أَوْ لَتَعُودُنَّ فِى مِلَّتِنَا ۖ فَأَوْحَىٰٓ إِلَيْهِمْ رَبُّهُمْ لَنُهْلِكَنَّ ٱلظَّٰلِمِينَ",
  "translation_en": "But they who denied the truth spoke [thus] unto their apostles: \"We shall most certainly expel you from our land, unless you return forthwith to our ways. Whereupon their Sustainer revealed this to His apostles: \"Most certainly shall We destroy these evildoers,",
  "audio_url": "https://cdn.islamic.network/quran/audio/128/ar.alafasy/1763.mp3",
  "segments": [],
  "segment_present": false
}
