{
  "verse_key": "12:62",
  "ayah_number": 1658,
  "text_uthmani": "وَقَالَ لِفِتْيَٰنِهِ ٱجْعَلُوا۟ بِضَٰعَتَهُمْ فِى رِحَالِهِمْ لَعَلَّهُمْ يَعْرِفُونَهَآ إِذَا ٱنقَلَبُوٓا۟ إِلَىٰٓ أَهْلِهِمْ لَعَلَّهُمْ يَرْجِعُونَ",
  "translation_en": "And [Joseph] said to his servants: \"Place their merchandise in their camel-packs, so that they may find it there when they come home, and hence be the more eager to return.",
  "audio_url": "https://cdn.islamic.network/quran/audio/128/ar.alafasy/1658.mp3",
  "segments": [],
  "segment_present": false
}
