{
  "verse_key": "2:280",
  "ayah_number": 287,
  "text_uthmani": "وَإِن كَانَ ذُو عُسْرَةٍۢ فَنَظِرَةٌ إِلَىٰ مَيْسَرَةٍۢ ۚ وَأَن تَصَدَّقُوا۟ خَيْرٌۭ لَّكُمْ ۖ إِن كُنتُمْ تَعْلَمُونَ",
  "translation_en": "If, however, [the debtor] is in straitened circumstances, [grant him] a delay until a time of ease; and it would be for your own good -if you but knew it -to remit [the debt entirely] by way of charity.",
  "audio_url": "https://cdn.islamic.network/quran/audio/128/ar.alafasy/287.mp3",
  "segments": [],
  "segment_present": false
}
