{
  "verse_key": "9:129",
  "ayah_number": 1364,
  "text_uthmani": "فَإِن تَوَلَّوْا۟ فَقُلْ حَسْبِىَ ٱللَّهُ لَآ إِلَٰهَ إِلَّا هُوَ ۖ عَلَيْهِ تَوَكَّلْتُ ۖ وَهُوَ رَبُّ ٱلْعَرْشِ ٱلْعَظِيمِ",
  "translation_en": "But if those [who are bent on denying the truth] turn away, say: \"God is enough for me! There is no- deity save Him. In Him have I placed my trust, for He is the Sustainer, in awesome almightiness enthroned.\"",
  "audio_url": "https://cdn.islamic.network/quran/audio/128/ar.alafasy/1364.mp3",
  "segments": [],
  "segment_present": false
}
