{
  "verse_key": "6:57",
  "ayah_number": 846,
  "text_uthmani": "قُلْ إِنِّى عَلَىٰ بَيِّنَةٍۢ مِّن رَّبِّى وَكَذَّبْتُم بِهِۦ ۚ مَا عِندِى مَا تَسْتَعْجِلُونَ بِهِۦٓ ۚ إِنِ ٱلْحُكْمُ إِلَّا لِلَّهِ ۖ يَقُصُّ ٱلْحَقَّ ۖ وَهُوَ خَيْرُ ٱلْفَٰصِلِينَ",
  "translation_en": "Say: \"Behold, I take my stand on a clear evidence from my Sustainer-and [so] it is to Him that you are giving the lie! Not in my power is that which [in your ignorance] you so hastily demand: judgment rests with none but God. He shall declare the truth, since it is He who is the best judge between truth and falsehood.\"",
  "audio_url": "https://cdn.islamic.network/quran/audio/128/ar.alafasy/846.mp3",
  "segments": [],
  "segment_present": false
}
