{
  "verse_key": "11:112",
  "ayah_number": 1585,
  "text_uthmani": "فَٱسْتَقِمْ كَمَآ أُمِرْتَ وَمَن تَابَ مَعَكَ وَلَا تَطْغَوْا۟ ۚ إِنَّهُۥ بِمَا تَعْمَلُونَ بَصِيرٌۭ",
  "translation_en": "Pursue, then, the right course, as thou hast been bidden [by God], together with all who, with thee, have turned unto Him; and let none of you behave in an overweening manner: for, verily, He sees all that you do.",
  "audio_url": "https://cdn.islamic.network/quran/audio/128/ar.alafasy/1585.mp3",
  "segments": [],
  "segment_present": false
}
