{
  "verse_key": "17:23",
  "ayah_number": 2052,
  "text_uthmani": "۞ وَقَضَىٰ رَبُّكَ أَلَّا تَعْبُدُوٓا۟ إِلَّآ إِيَّاهُ وَبِٱلْوَٰلِدَيْنِ إِحْسَٰنًا ۚ إِمَّا يَبْلُغَنَّ عِندَكَ ٱلْكِبَرَ أَحَدُهُمَآ أَوْ كِلَاهُمَا فَلَا تَقُل لَّهُمَآ أُفٍّۢ وَلَا تَنْهَرْهُمَا وَقُل لَّهُمَا قَوْلًۭا كَرِيمًۭا",
  "translation_en": "for thy Sustainer has ordained that you shall worship none but Him. And do good unto [thy] parents. Should one of them, or both, attain to old age in thy care, never say \"Ugh\" to them or scold them, but [always] speak unto them with reverent speech,",
  "audio_url": "https://cdn.islamic.network/quran/audio/128/ar.alafasy/2052.mp3",
  "segments": [],
  "segment_present": false
}
