{
  "verse_key": "43:17",
  "ayah_number": 4342,
  "text_uthmani": "وَإِذَا بُشِّرَ أَحَدُهُم بِمَا ضَرَبَ لِلرَّحْمَٰنِ مَثَلًۭا ظَلَّ وَجْهُهُۥ مُسْوَدًّۭا وَهُوَ كَظِيمٌ",
  "translation_en": "For [thus it is:] if any of them is given the glad tiding of [the birth of] what he so readily attributes to the Most Gracious, his face darkens, and he is filled with suppressed anger:",
  "audio_url": "https://cdn.islamic.network/quran/audio/128/ar.alafasy/4342.mp3",
  "segments": [],
  "segment_present": false
}
