{
  "verse_key": "62:1",
  "ayah_number": 5178,
  "text_uthmani": "بِسْمِ ٱللَّهِ ٱلرَّحْمَٰنِ ٱلرَّحِيمِ يُسَبِّحُ لِلَّهِ مَا فِى ٱلسَّمَٰوَٰتِ وَمَا فِى ٱلْأَرْضِ ٱلْمَلِكِ ٱلْقُدُّوسِ ٱلْعَزِيزِ ٱلْحَكِيمِ",
  "translation_en": "ALL THAT IS in the heavens and all that is on earth extols the limitless glory of God, the Sovereign Supreme, the Holy, the Almighty, the Wise!",
  "audio_url": "https://cdn.islamic.network/quran/audio/128/ar.alafasy/5178.mp3",
  "segments": [],
  "segment_present": false
}
