{
  "verse_key": "58:5",
  "ayah_number": 5109,
  "text_uthmani": "إِنَّ ٱلَّذِينَ يُحَآدُّونَ ٱللَّهَ وَرَسُولَهُۥ كُبِتُوا۟ كَمَا كُبِتَ ٱلَّذِينَ مِن قَبْلِهِمْ ۚ وَقَدْ أَنزَلْنَآ ءَايَٰتٍۭ بَيِّنَٰتٍۢ ۚ وَلِلْكَٰفِرِينَ عَذَابٌۭ مُّهِينٌۭ",
  "translation_en": "Verily, those who contend against God and His Apostle shall be brought low even as those [evildoers] who lived before them were brought low after We had bestowed [on them] clear messages from on high. And [so,] for those who deny the truth there will be shameful suffering in store",
  "audio_url": "https://cdn.islamic.network/quran/audio/128/ar.alafasy/5109.mp3",
  "segments": [],
  "segment_present": false
}
