{
  "verse_key": "3:174",
  "ayah_number": 467,
  "text_uthmani": "فَٱنقَلَبُوا۟ بِنِعْمَةٍۢ مِّنَ ٱللَّهِ وَفَضْلٍۢ لَّمْ يَمْسَسْهُمْ سُوٓءٌۭ وَٱتَّبَعُوا۟ رِضْوَٰنَ ٱللَّهِ ۗ وَٱللَّهُ ذُو فَضْلٍ عَظِيمٍ",
  "translation_en": "- and returned [from the battle] with God's blessings and bounty, without having been touched by evil: for they had been striving after God's goodly acceptance - and God is limitless in His great bounty.",
  "audio_url": "https://cdn.islamic.network/quran/audio/128/ar.alafasy/467.mp3",
  "segments": [],
  "segment_present": false
}
